etrading/__init__.py
etrading/etrading.py
etrading-0.0.0.dist-info/AUTHORS.rst
etrading-0.0.0.dist-info/LICENSE
etrading-0.0.0.dist-info/METADATA
etrading-0.0.0.dist-info/WHEEL
etrading-0.0.0.dist-info/entry_points.txt
etrading-0.0.0.dist-info/top_level.txt
etrading-0.0.0.dist-info/RECORD
