Metadata-Version: 2.1
Name: etrading
Version: 0.0.0
Summary: Module for live trading via Metatrader (with MQL5)
Home-page: https://github.com/serginc21/etrading
Author: Sergi Novellas
Author-email: sernocr@gmail.com
License: MIT license
Keywords: etrading
Platform: UNKNOWN
Classifier: Development Status :: 2 - Pre-Alpha
Classifier: Intended Audience :: Developers
Classifier: License :: OSI Approved :: MIT License
Classifier: Natural Language :: English
Classifier: Programming Language :: Python :: 3
Classifier: Programming Language :: Python :: 3.5
Classifier: Programming Language :: Python :: 3.6
Classifier: Programming Language :: Python :: 3.7
Classifier: Programming Language :: Python :: 3.8
Requires-Python: >=3.6
Requires-Dist: Click (>=7.0)
